{
  "main": {
    "id": "8039e94921ab8ebb",
    "type": "split",
    "children": [
      {
        "id": "b217b2cfe98789cd",
        "type": "tabs",
        "children": [
          {
            "id": "59e7b43a788f784b",
            "type": "leaf",
            "state": {
              "type": "markdown",
              "state": {
                "file": "Flutter/Package/BLoC/BlocProvider.md",
                "mode": "source",
                "source": false
              }
            }
          }
        ]
      }
    ],
    "direction": "vertical"
  },
  "left": {
    "id": "084087ea922fa881",
    "type": "split",
    "children": [
      {
        "id": "4ce1ebda57325ef8",
        "type": "tabs",
        "children": [
          {
            "id": "dc33a1bf87f31cee",
            "type": "leaf",
            "state": {
              "type": "file-explorer",
              "state": {
                "sortOrder": "alphabetical"
              }
            }
          },
          {
            "id": "214e3485da6b8243",
            "type": "leaf",
            "state": {
              "type": "search",
              "state": {
                "query": "",
                "matchingCase": false,
                "explainSearch": false,
                "collapseAll": false,
                "extraContext": false,
                "sortOrder": "alphabetical"
              }
            }
          },
          {
            "id": "f370311e912c6ceb",
            "type": "leaf",
            "state": {
              "type": "bookmarks",
              "state": {}
            }
          }
        ]
      }
    ],
    "direction": "horizontal",
    "width": 200
  },
  "right": {
    "id": "74c5594cf34ccf29",
    "type": "split",
    "children": [
      {
        "id": "77393066e460f9d4",
        "type": "tabs",
        "children": [
          {
            "id": "cee54593388470dc",
            "type": "leaf",
            "state": {
              "type": "backlink",
              "state": {
                "file": "Flutter/Package/BLoC/BlocProvider.md",
                "collapseAll": false,
                "extraContext": false,
                "sortOrder": "alphabetical",
                "showSearch": false,
                "searchQuery": "",
                "backlinkCollapsed": false,
                "unlinkedCollapsed": true
              }
            }
          },
          {
            "id": "63fd0531be36919d",
            "type": "leaf",
            "state": {
              "type": "outgoing-link",
              "state": {
                "file": "Flutter/Package/BLoC/BlocProvider.md",
                "linksCollapsed": false,
                "unlinkedCollapsed": true
              }
            }
          },
          {
            "id": "0034fd3b64105635",
            "type": "leaf",
            "state": {
              "type": "tag",
              "state": {
                "sortOrder": "frequency",
                "useHierarchy": true
              }
            }
          },
          {
            "id": "f4f8ef8334e13f12",
            "type": "leaf",
            "state": {
              "type": "outline",
              "state": {
                "file": "Flutter/Package/BLoC/BlocProvider.md"
              }
            }
          }
        ]
      }
    ],
    "direction": "horizontal",
    "width": 300,
    "collapsed": true
  },
  "left-ribbon": {
    "hiddenItems": {
      "switcher:Відкрити провідник файлів": false,
      "graph:Граф": false,
      "canvas:Створити нове полотно": false,
      "daily-notes:Сьогоднішня нотатка": false,
      "templates:Вставити шаблон": false,
      "command-palette:Відкрити меню команд": false,
      "markdown-importer:Імпорт Markdown-файлів": false,
      "templater-obsidian:Templater": false
    }
  },
  "active": "59e7b43a788f784b",
  "lastOpenFiles": [
    "Pasted image 20240605121421.png",
    "Pasted image 20240605121236.png",
    "Pasted image 20240605121012.png",
    "Flutter/Віджети/Що таке Widget.md",
    "Flutter/HTTP and BLoC.md",
    "Dart/Класи/Future.md",
    "Dart/Dart info.md",
    "Dart/Класи/Без назви",
    "Dart/Класи",
    "Dart/Інформація/Функції.md",
    "Dart/Інформація/Структура Dart.md",
    "Dart/Інформація/Списки данних.md",
    "Dart/Інформація/Перетворення типів.md",
    "Dart/Інформація/Об'єкти.md",
    "Dart/Інформація/Змінні та ключові слова.md",
    "Dart/Інформація/Арифметичні дії.md",
    "Flutter/Класи/Клас для роботи з JSON.md",
    "API.md",
    "Postman.md",
    "().md",
    "Flutter/Package/BLoC/MultiBlocProvider.md",
    "Flutter/Package/BLoC/BlocProvider.md",
    "Flutter/Package/BLoC/BlocBuilder.md",
    "Flutter/Package/BLoC/Bloc State.md",
    "Flutter/Package/BLoC/Bloc.md",
    "Flutter/@override.md",
    "Flutter/Іменовані аргументи.md",
    "Flutter/Початок роботи.md",
    "Flutter/Метода/Методи Flutter/build(BuildContext context).md",
    "Flutter/Метода/Інформація.md",
    "Flutter/Package/BLoC",
    "Flutter/Властивості",
    "Flutter/Метода/Методи Flutter",
    "Flutter/Віджети/Без назви",
    "Flutter/Класи",
    "Flutter/Package",
    "Flutter/Метода",
    "Flutter/Віджети",
    "Без назви.canvas",
    "Без назви 1.canvas"
  ]
}